HISTORY.rst
README.rst
django_session_header_11/__init__.py
django_session_header_11/authentication.py
django_session_header_11/middleware.py
tests/conftest.py
tests/test_authentication.py
tests/test_middleware.py
django_session_header_11-1.0.1.dist-info/LICENSE
django_session_header_11-1.0.1.dist-info/WHEEL
django_session_header_11-1.0.1.dist-info/METADATA
django_session_header_11-1.0.1.dist-info/RECORD
